{
    "key": "group_5d80d38c44b1c",
    "title": "Image Accordion",
    "fields": [
        {
            "key": "field_5d8385b527cf8",
            "label": "Content",
            "name": "",
            "type": "tab",
            "instructions": "",
            "required": 0,
            "conditional_logic": 0,
            "wrapper": {
                "width": "",
                "class": "",
                "id": ""
            },
            "placement": "top",
            "endpoint": 0
        },
        {
            "key": "field_5d8375f658a0a",
            "label": "Styles",
            "name": "acfb_image_accordion_styles",
            "type": "select",
            "instructions": "",
            "required": 0,
            "conditional_logic": 0,
            "wrapper": {
                "width": "",
                "class": "",
                "id": ""
            },
            "choices": {
                "row": "Vertical",
                "column": "Horizontal"
            },
            "default_value": [
                "row"
            ],
            "allow_null": 0,
            "multiple": 0,
            "ui": 0,
            "return_format": "value",
            "ajax": 0,
            "placeholder": ""
        },
        {
            "key": "field_5d8383e2d7d31",
            "label": "Height",
            "name": "acfb_image_accordion_height",
            "type": "range",
            "instructions": "",
            "required": 0,
            "conditional_logic": 0,
            "wrapper": {
                "width": "",
                "class": "",
                "id": ""
            },
            "default_value": 500,
            "min": "",
            "max": 1000,
            "step": "",
            "prepend": "",
            "append": "px"
        },
        {
            "key": "field_5d83765c2c181",
            "label": "Gutter Space",
            "name": "acfb_image_accordion_gutter",
            "type": "range",
            "instructions": "",
            "required": 0,
            "conditional_logic": 0,
            "wrapper": {
                "width": "",
                "class": "",
                "id": ""
            },
            "default_value": 0,
            "min": "",
            "max": 50,
            "step": "",
            "prepend": "",
            "append": "px"
        },
        {
            "key": "field_5d83757558a04",
            "label": "Image Accordion",
            "name": "acfb_image_accordion",
            "type": "repeater",
            "instructions": "",
            "required": 0,
            "conditional_logic": 0,
            "wrapper": {
                "width": "",
                "class": "",
                "id": ""
            },
            "collapsed": "",
            "min": 0,
            "max": 0,
            "layout": "block",
            "button_label": "Add Image",
            "sub_fields": [
                {
                    "key": "field_5d83758858a05",
                    "label": "Image",
                    "name": "acfb_image_accordion_image",
                    "type": "image",
                    "instructions": "",
                    "required": 0,
                    "conditional_logic": 0,
                    "wrapper": {
                        "width": "",
                        "class": "",
                        "id": ""
                    },
                    "return_format": "url",
                    "preview_size": "medium",
                    "library": "all",
                    "min_width": "",
                    "min_height": "",
                    "min_size": "",
                    "max_width": "",
                    "max_height": "",
                    "max_size": "",
                    "mime_types": ""
                },
                {
                    "key": "field_5d8375a258a06",
                    "label": "Title",
                    "name": "acfb_image_accordion_title",
                    "type": "text",
                    "instructions": "",
                    "required": 0,
                    "conditional_logic": 0,
                    "wrapper": {
                        "width": "",
                        "class": "",
                        "id": ""
                    },
                    "default_value": "Title",
                    "placeholder": "Title",
                    "prepend": "",
                    "append": "",
                    "maxlength": ""
                },
                {
                    "key": "field_5d8375b558a07",
                    "label": "Content",
                    "name": "acfb_image_accordion_content",
                    "type": "textarea",
                    "instructions": "",
                    "required": 0,
                    "conditional_logic": 0,
                    "wrapper": {
                        "width": "",
                        "class": "",
                        "id": ""
                    },
                    "default_value": "Click edit button to change this text. Lorem ipsum dolor sit amet, consectetur adipiscing elit. Ut elit tellus, luctus nec ullamcorper mattis, pulvinar dapibus leo.",
                    "placeholder": "",
                    "maxlength": "",
                    "rows": "",
                    "new_lines": ""
                },
                {
                    "key": "field_5d8375c358a08",
                    "label": "Button Text",
                    "name": "acfb_image_accordion_button_text",
                    "type": "text",
                    "instructions": "",
                    "required": 0,
                    "conditional_logic": 0,
                    "wrapper": {
                        "width": "",
                        "class": "",
                        "id": ""
                    },
                    "default_value": "Button Text",
                    "placeholder": "Button Text",
                    "prepend": "",
                    "append": "",
                    "maxlength": ""
                },
                {
                    "key": "field_5d8375d558a09",
                    "label": "Button Url",
                    "name": "acfb_image_accordion_button_url",
                    "type": "url",
                    "instructions": "",
                    "required": 0,
                    "conditional_logic": 0,
                    "wrapper": {
                        "width": "",
                        "class": "",
                        "id": ""
                    },
                    "default_value": "#",
                    "placeholder": "#"
                },
                {
                    "key": "field_5dca8c28bf103",
                    "label": "Content Width",
                    "name": "acfb_image_accordion_cw",
                    "type": "range",
                    "instructions": "",
                    "required": 0,
                    "conditional_logic": 0,
                    "wrapper": {
                        "width": "",
                        "class": "",
                        "id": ""
                    },
                    "default_value": 100,
                    "min": 50,
                    "max": 100,
                    "step": 1,
                    "prepend": "",
                    "append": "%"
                },
                {
                    "key": "field_5dca8ba8bf101",
                    "label": "Content Vertical Align",
                    "name": "acfb_image_accordion_cva",
                    "type": "button_group",
                    "instructions": "",
                    "required": 0,
                    "conditional_logic": 0,
                    "wrapper": {
                        "width": "",
                        "class": "",
                        "id": ""
                    },
                    "choices": {
                        "flex-start": "Top",
                        "center": "Center",
                        "flex-end": "Bottom"
                    },
                    "allow_null": 0,
                    "default_value": "center",
                    "layout": "horizontal",
                    "return_format": "value"
                },
                {
                    "key": "field_5dca8bfabf102",
                    "label": "Content Horizontal Align",
                    "name": "acfb_image_accordion_cha",
                    "type": "button_group",
                    "instructions": "",
                    "required": 0,
                    "conditional_logic": 0,
                    "wrapper": {
                        "width": "",
                        "class": "",
                        "id": ""
                    },
                    "choices": {
                        "flex-start": "Left",
                        "center": "Center",
                        "flex-end": "Right"
                    },
                    "allow_null": 0,
                    "default_value": "center",
                    "layout": "horizontal",
                    "return_format": "value"
                }
            ]
        },
        {
            "key": "field_5d8385c527cf9",
            "label": "Design",
            "name": "",
            "type": "tab",
            "instructions": "",
            "required": 0,
            "conditional_logic": 0,
            "wrapper": {
                "width": "",
                "class": "",
                "id": ""
            },
            "placement": "top",
            "endpoint": 0
        },
        {
            "key": "field_5eaad09df0b4d",
            "label": "Typography",
            "name": "",
            "type": "accordion",
            "instructions": "",
            "required": 0,
            "conditional_logic": 0,
            "wrapper": {
                "width": "",
                "class": "",
                "id": ""
            },
            "open": 0,
            "multi_expand": 0,
            "endpoint": 0
        },
        {
            "key": "field_5eaad0cdf0b50",
            "label": "Title",
            "name": "acfb_image_accordion_title_typo",
            "type": "typography",
            "instructions": "",
            "required": 0,
            "conditional_logic": 0,
            "wrapper": {
                "width": "",
                "class": "",
                "id": ""
            },
            "font_family_enable": 0,
            "font_family": "default",
            "font_size": 32,
            "font_weight": "default",
            "font_transform": "default",
            "font_style": "default",
            "font_decoration": "default",
            "font_line_height": "0.1",
            "font_letter_spacing": 0
        },
        {
            "key": "field_5eaad0eef0b51",
            "label": "Content",
            "name": "acfb_image_accordion_content_typo",
            "type": "typography",
            "instructions": "",
            "required": 0,
            "conditional_logic": 0,
            "wrapper": {
                "width": "",
                "class": "",
                "id": ""
            },
            "font_family_enable": 0,
            "font_family": "default",
            "font_size": 18,
            "font_weight": "default",
            "font_transform": "default",
            "font_style": "default",
            "font_decoration": "default",
            "font_line_height": "0.1",
            "font_letter_spacing": 0
        },
        {
            "key": "field_5eaad10bf0b52",
            "label": "Button",
            "name": "acfb_image_accordion_button_typo",
            "type": "typography",
            "instructions": "",
            "required": 0,
            "conditional_logic": 0,
            "wrapper": {
                "width": "",
                "class": "",
                "id": ""
            },
            "font_family_enable": 0,
            "font_family": "default",
            "font_size": 19,
            "font_weight": "default",
            "font_transform": "default",
            "font_style": "default",
            "font_decoration": "default",
            "font_line_height": "0.1",
            "font_letter_spacing": 0
        },
        {
            "key": "field_5eaad0a4f0b4e",
            "label": "Colors",
            "name": "",
            "type": "accordion",
            "instructions": "",
            "required": 0,
            "conditional_logic": 0,
            "wrapper": {
                "width": "",
                "class": "",
                "id": ""
            },
            "open": 0,
            "multi_expand": 0,
            "endpoint": 0
        },
        {
            "key": "field_5da98e2f25a0b",
            "label": "Overlay Color",
            "name": "acfb_image_accordion_overlay_color",
            "type": "color_picker",
            "instructions": "",
            "required": 0,
            "conditional_logic": 0,
            "wrapper": {
                "width": "",
                "class": "",
                "id": ""
            },
            "default_value": "#000000"
        },
        {
            "key": "field_5dc96e7eb99e8",
            "label": "Overlay Active Opacity",
            "name": "acfb_image_accordion_overlay_active_opacity",
            "type": "range",
            "instructions": "",
            "required": 0,
            "conditional_logic": 0,
            "wrapper": {
                "width": "",
                "class": "",
                "id": ""
            },
            "default_value": "0.5",
            "min": "0.1",
            "max": "0.9",
            "step": ".1",
            "prepend": "",
            "append": ""
        },
        {
            "key": "field_5dc96a88163e5",
            "label": "Overlay Inactive Opacity",
            "name": "acfb_image_accordion_overlay_inactive_opacity",
            "type": "range",
            "instructions": "",
            "required": 0,
            "conditional_logic": 0,
            "wrapper": {
                "width": "",
                "class": "",
                "id": ""
            },
            "default_value": "0.3",
            "min": "0.1",
            "max": "0.9",
            "step": ".1",
            "prepend": "",
            "append": ""
        },
        {
            "key": "field_5d8385e527cfa",
            "label": "Title Color",
            "name": "acfb_image_accordion_title_color",
            "type": "color_picker",
            "instructions": "",
            "required": 0,
            "conditional_logic": 0,
            "wrapper": {
                "width": "",
                "class": "",
                "id": ""
            },
            "default_value": "#ffffff"
        },
        {
            "key": "field_5d83863227cfc",
            "label": "Content Color",
            "name": "acfb_image_accordion_content_color",
            "type": "color_picker",
            "instructions": "",
            "required": 0,
            "conditional_logic": 0,
            "wrapper": {
                "width": "",
                "class": "",
                "id": ""
            },
            "default_value": "#ffffff"
        },
        {
            "key": "field_5d8386a927cfe",
            "label": "Button Background Color",
            "name": "acfb_image_accordion_button_background_color",
            "type": "color_picker",
            "instructions": "",
            "required": 0,
            "conditional_logic": 0,
            "wrapper": {
                "width": "",
                "class": "",
                "id": ""
            },
            "default_value": "#e0e0e0"
        },
        {
            "key": "field_5d8386b927cff",
            "label": "Button Text Color",
            "name": "acfb_image_accordion_button_text_color",
            "type": "color_picker",
            "instructions": "",
            "required": 0,
            "conditional_logic": 0,
            "wrapper": {
                "width": "",
                "class": "",
                "id": ""
            },
            "default_value": "#191e23"
        },
        {
            "key": "field_5d8386c627d00",
            "label": "Button Background Hover Color",
            "name": "acfb_image_accordion_button_background_hover_color",
            "type": "color_picker",
            "instructions": "",
            "required": 0,
            "conditional_logic": 0,
            "wrapper": {
                "width": "",
                "class": "",
                "id": ""
            },
            "default_value": "#e0e0e0"
        },
        {
            "key": "field_5d8386d827d01",
            "label": "Button Text Hover Color",
            "name": "acfb_image_accordion_button_text_hover_color",
            "type": "color_picker",
            "instructions": "",
            "required": 0,
            "conditional_logic": 0,
            "wrapper": {
                "width": "",
                "class": "",
                "id": ""
            },
            "default_value": "#191e23"
        },
        {
            "key": "field_5eaad0acf0b4f",
            "label": "Spacing",
            "name": "",
            "type": "accordion",
            "instructions": "",
            "required": 0,
            "conditional_logic": 0,
            "wrapper": {
                "width": "",
                "class": "",
                "id": ""
            },
            "open": 0,
            "multi_expand": 0,
            "endpoint": 0
        },
        {
            "key": "field_5eaad16271803",
            "label": "Margin",
            "name": "acfb_image_accordion_margin",
            "type": "margin",
            "instructions": "",
            "required": 0,
            "conditional_logic": 0,
            "wrapper": {
                "width": "",
                "class": "",
                "id": ""
            },
            "margin_enable": 0,
            "margin_top": "",
            "margin_right": "",
            "margin_bottom": "",
            "margin_left": ""
        },
        {
            "key": "field_5eaad17071804",
            "label": "Padding",
            "name": "acfb_image_accordion_padding",
            "type": "padding",
            "instructions": "",
            "required": 0,
            "conditional_logic": 0,
            "wrapper": {
                "width": "",
                "class": "",
                "id": ""
            },
            "padding_enable": 0,
            "padding_top": "",
            "padding_right": "",
            "padding_bottom": "",
            "padding_left": ""
        },
        {
            "key": "field_5eaad196f6d82",
            "label": "Inner Padding",
            "name": "acfb_image_accordion_inner_padding",
            "type": "padding",
            "instructions": "",
            "required": 0,
            "conditional_logic": 0,
            "wrapper": {
                "width": "",
                "class": "",
                "id": ""
            },
            "padding_enable": 0,
            "padding_top": 20,
            "padding_right": 20,
            "padding_bottom": 20,
            "padding_left": 20
        }
    ],
    "location": [
        [
            {
                "param": "block",
                "operator": "==",
                "value": "acf\/acfb-image-accordion"
            }
        ]
    ],
    "menu_order": 0,
    "position": "normal",
    "style": "default",
    "label_placement": "top",
    "instruction_placement": "label",
    "hide_on_screen": "",
    "active": 1,
    "description": "",
    "modified": 1588253112
}