{
    "key": "group_5cc6b8e86e751",
    "title": "Progress Bar",
    "fields": [
        {
            "key": "field_5cc835ec452d9",
            "label": "Content",
            "name": "",
            "type": "tab",
            "instructions": "",
            "required": 0,
            "conditional_logic": 0,
            "wrapper": {
                "width": "",
                "class": "",
                "id": ""
            },
            "placement": "top",
            "endpoint": 0
        },
        {
            "key": "field_5cc6bdabf9129",
            "label": "Title",
            "name": "acfb_progressbar_title",
            "type": "text",
            "instructions": "",
            "required": 0,
            "conditional_logic": 0,
            "wrapper": {
                "width": "",
                "class": "",
                "id": ""
            },
            "default_value": "Title Here",
            "placeholder": "Title Here",
            "prepend": "",
            "append": "",
            "maxlength": ""
        },
        {
            "key": "field_5cc6bde9f912a",
            "label": "Percentage",
            "name": "acfb_progressbar_percentage",
            "type": "range",
            "instructions": "",
            "required": 0,
            "conditional_logic": 0,
            "wrapper": {
                "width": "",
                "class": "",
                "id": ""
            },
            "default_value": 50,
            "min": "",
            "max": "",
            "step": "",
            "prepend": "",
            "append": "%"
        },
        {
            "key": "field_5cc6be0df912b",
            "label": "Display Percentage",
            "name": "acfb_progressbar_display_percentage",
            "type": "true_false",
            "instructions": "",
            "required": 0,
            "conditional_logic": 0,
            "wrapper": {
                "width": "",
                "class": "",
                "id": ""
            },
            "message": "Yes \/ No",
            "default_value": 1,
            "ui": 0,
            "ui_on_text": "",
            "ui_off_text": ""
        },
        {
            "key": "field_5cc6bee498c0c",
            "label": "Inner Text",
            "name": "acfb_progressbar_inner_text",
            "type": "text",
            "instructions": "",
            "required": 0,
            "conditional_logic": 0,
            "wrapper": {
                "width": "",
                "class": "",
                "id": ""
            },
            "default_value": "Web Designer",
            "placeholder": "Web Designer",
            "prepend": "",
            "append": "",
            "maxlength": ""
        },
        {
            "key": "field_5cc838e1452da",
            "label": "Design",
            "name": "",
            "type": "tab",
            "instructions": "",
            "required": 0,
            "conditional_logic": 0,
            "wrapper": {
                "width": "",
                "class": "",
                "id": ""
            },
            "placement": "top",
            "endpoint": 0
        },
        {
            "key": "field_5eaa87554e5e9",
            "label": "Typography",
            "name": "",
            "type": "accordion",
            "instructions": "",
            "required": 0,
            "conditional_logic": 0,
            "wrapper": {
                "width": "",
                "class": "",
                "id": ""
            },
            "open": 0,
            "multi_expand": 0,
            "endpoint": 0
        },
        {
            "key": "field_5eaa87864e5eb",
            "label": "Text",
            "name": "acfb_progressbar_text_typo",
            "type": "typography",
            "instructions": "",
            "required": 0,
            "conditional_logic": 0,
            "wrapper": {
                "width": "",
                "class": "",
                "id": ""
            },
            "font_family_enable": 0,
            "font_family": "default",
            "font_size": 14,
            "font_weight": "default",
            "font_transform": "default",
            "font_style": "default",
            "font_decoration": "default",
            "font_line_height": "0.1",
            "font_letter_spacing": 0
        },
        {
            "key": "field_5eaa87a44e5ec",
            "label": "Ttile",
            "name": "acfb_progressbar_title_typo",
            "type": "typography",
            "instructions": "",
            "required": 0,
            "conditional_logic": 0,
            "wrapper": {
                "width": "",
                "class": "",
                "id": ""
            },
            "font_family_enable": 0,
            "font_family": "default",
            "font_size": 16,
            "font_weight": "default",
            "font_transform": "default",
            "font_style": "default",
            "font_decoration": "default",
            "font_line_height": "0.1",
            "font_letter_spacing": 0
        },
        {
            "key": "field_5eaa87604e5ea",
            "label": "Colors",
            "name": "",
            "type": "accordion",
            "instructions": "",
            "required": 0,
            "conditional_logic": 0,
            "wrapper": {
                "width": "",
                "class": "",
                "id": ""
            },
            "open": 0,
            "multi_expand": 0,
            "endpoint": 0
        },
        {
            "key": "field_5cc6c8983d17c",
            "label": "Bar Color",
            "name": "acfb_progressbar_bg_color",
            "type": "color_picker",
            "instructions": "",
            "required": 0,
            "conditional_logic": 0,
            "wrapper": {
                "width": "",
                "class": "",
                "id": ""
            },
            "default_value": "#6ec1e4"
        },
        {
            "key": "field_5cc6c8f93d17d",
            "label": "Background Color",
            "name": "acfb_progressbar_unactive_bg_color",
            "type": "color_picker",
            "instructions": "",
            "required": 0,
            "conditional_logic": 0,
            "wrapper": {
                "width": "",
                "class": "",
                "id": ""
            },
            "default_value": "#f3f4f5"
        },
        {
            "key": "field_5cc6c94e3d17e",
            "label": "Text Color",
            "name": "acfb_progressbar_text_color",
            "type": "color_picker",
            "instructions": "",
            "required": 0,
            "conditional_logic": 0,
            "wrapper": {
                "width": "",
                "class": "",
                "id": ""
            },
            "default_value": "#FFFFFF"
        },
        {
            "key": "field_5cc6c9ba3d180",
            "label": "Title Color",
            "name": "acfb_progressbar_title_color",
            "type": "color_picker",
            "instructions": "",
            "required": 0,
            "conditional_logic": 0,
            "wrapper": {
                "width": "",
                "class": "",
                "id": ""
            },
            "default_value": "#191e23"
        },
        {
            "key": "field_5eaa87efe3903",
            "label": "Spacing",
            "name": "",
            "type": "accordion",
            "instructions": "",
            "required": 0,
            "conditional_logic": 0,
            "wrapper": {
                "width": "",
                "class": "",
                "id": ""
            },
            "open": 0,
            "multi_expand": 0,
            "endpoint": 0
        },
        {
            "key": "field_5eaa87ffe3904",
            "label": "Margin",
            "name": "acfb_progressbar_margin",
            "type": "margin",
            "instructions": "",
            "required": 0,
            "conditional_logic": 0,
            "wrapper": {
                "width": "",
                "class": "",
                "id": ""
            },
            "margin_enable": 0,
            "margin_top": "",
            "margin_right": "",
            "margin_bottom": "",
            "margin_left": ""
        },
        {
            "key": "field_5eaa8814e3905",
            "label": "Padding",
            "name": "acfb_progressbar_padding",
            "type": "padding",
            "instructions": "",
            "required": 0,
            "conditional_logic": 0,
            "wrapper": {
                "width": "",
                "class": "",
                "id": ""
            },
            "padding_enable": 0,
            "padding_top": "",
            "padding_right": "",
            "padding_bottom": "",
            "padding_left": ""
        }
    ],
    "location": [
        [
            {
                "param": "block",
                "operator": "==",
                "value": "acf\/acfb-progressbar"
            }
        ]
    ],
    "menu_order": 0,
    "position": "normal",
    "style": "default",
    "label_placement": "top",
    "instruction_placement": "label",
    "hide_on_screen": "",
    "active": 1,
    "description": "",
    "modified": 1588325844
}